setup.py
JES12132018_AssetInspectionApps/__init__.py
JES12132018_AssetInspectionApps/core_function_hydrant.py
JES12132018_AssetInspectionApps/core_function_manhole.py
JES12132018_AssetInspectionApps/core_function_stormdrain.py
JES12132018_AssetInspectionApps/core_function_valve.py
JES12132018_AssetInspectionApps/gui_Project_hydrant.py
JES12132018_AssetInspectionApps/gui_Project_manhole.py
JES12132018_AssetInspectionApps/gui_Project_stormdrain.py
JES12132018_AssetInspectionApps/gui_Project_valve.py
JES12132018_AssetInspectionApps/main_Script_hydrant.py
JES12132018_AssetInspectionApps/main_Script_manhole.py
JES12132018_AssetInspectionApps/main_Script_stormdrain.py
JES12132018_AssetInspectionApps/main_Script_valve.py
JES12132018_AssetInspectionApps.egg-info/PKG-INFO
JES12132018_AssetInspectionApps.egg-info/SOURCES.txt
JES12132018_AssetInspectionApps.egg-info/dependency_links.txt
JES12132018_AssetInspectionApps.egg-info/not-zip-safe
JES12132018_AssetInspectionApps.egg-info/requires.txt
JES12132018_AssetInspectionApps.egg-info/top_level.txt