Metadata-Version: 1.0
Name: JES12132018-AssetInspectionApps
Version: 1.0
Summary: JES12132018_AssetInspectionApps
Home-page: https://www.gwinnettcounty.com/web/gwinnett/departments/publicutilities
Author: eric swett
Author-email: eric.swett@gwinnettcounty.com
License: BSD
Platform: UNKNOWN
